rptodo/__init__.py
rptodo/__main__.py
rptodo/cli.py
rptodo/config.py
rptodo/database.py
rptodo/rptodo.py
rptodo-0.1.dist-info/licenses/LICENSE
rptodo-0.1.dist-info/METADATA
rptodo-0.1.dist-info/WHEEL
rptodo-0.1.dist-info/entry_points.txt
rptodo-0.1.dist-info/top_level.txt
rptodo-0.1.dist-info/RECORD
