Metadata-Version: 2.4
Name: rptodo
Version: 0.1
Summary: RP To-Do is a command-line interface application built with Typer to help you manage your to-do list.
Author: CryptoKingXavier
Author-email: cryptokingxavier001@gmail.com
License: MIT
Keywords: python packaging cli utilities todo
Classifier: Intended Audience :: Developers
Classifier: License :: OSI Approved :: MIT License
Classifier: Programming Language :: Python :: 3
Classifier: Programming Language :: Python :: 3.10
Classifier: Programming Language :: Python :: 3.11
Classifier: Programming Language :: Python :: 3.12
Classifier: Programming Language :: Python :: 3.13
Classifier: Operating System :: OS Independent
Classifier: Topic :: Software Development :: Libraries
Requires-Python: >=3.10
License-File: LICENSE
Requires-Dist: click
Requires-Dist: typer
Requires-Dist: wheel
Requires-Dist: colorama
Requires-Dist: shellingham
Requires-Dist: python-dotenv
Provides-Extra: dev
Requires-Dist: pytest; extra == "dev"
Requires-Dist: mypy; extra == "dev"
Requires-Dist: twine; extra == "dev"
Requires-Dist: snoop; extra == "dev"
Requires-Dist: setuptools; extra == "dev"
Dynamic: author
Dynamic: author-email
Dynamic: classifier
Dynamic: description
Dynamic: description-content-type
Dynamic: keywords
Dynamic: license
Dynamic: license-file
Dynamic: provides-extra
Dynamic: requires-dist
Dynamic: requires-python
Dynamic: summary
